<ti:work xmlns:ti="http://chs.harvard.edu/xmlns/cts" groupUrn="urn:cts:latinLit:tmp1434" xml:lang="lat" urn="urn:cts:latinLit:tmp1434.tmp1434">
  <ti:title xml:lang="eng">Exhortatio Humilitatis (Incertus) (Appendix X)</ti:title>
  <ti:edition urn="urn:cts:latinLit:tmp1434.tmp1434.opp-lat1" workUrn="urn:cts:latinLit:tmp1434.tmp1434">
    <ti:label xml:lang="eng">Exhortatio Humilitatis (Incertus) (Appendix X)</ti:label>
    <ti:description xml:lang="eng">Isidorus Hispalensis, Exhortatio Humilitatis (Incertus) (Appendix X)</ti:description>
  </ti:edition>
</ti:work>
