<ti:work xmlns:ti="http://chs.harvard.edu/xmlns/cts" groupUrn="urn:cts:latinLit:tmp1101" xml:lang="lat" urn="urn:cts:latinLit:tmp1101.tmp1101">
  <ti:title xml:lang="eng">Codex Canonum Ecclesiae Universae. Concilii Nicaeni Oecumenici I</ti:title>
  <ti:edition urn="urn:cts:latinLit:tmp1101.tmp1101.opp-lat1" workUrn="urn:cts:latinLit:tmp1101.tmp1101">
    <ti:label xml:lang="eng">Codex Canonum Ecclesiae Universae. Concilii Nicaeni Oecumenici I</ti:label>
    <ti:description xml:lang="eng">, Codex Canonum Ecclesiae Universae. Concilii Nicaeni Oecumenici I</ti:description>
  </ti:edition>
</ti:work>
