<ti:work xmlns:ti="http://chs.harvard.edu/xmlns/cts" groupUrn="urn:cts:latinLit:tmp1353" xml:lang="lat" urn="urn:cts:latinLit:tmp1353.tmp1353">
  <ti:title xml:lang="eng">Interpretatio Mystica Progenitorum Christi</ti:title>
  <ti:edition urn="urn:cts:latinLit:tmp1353.tmp1353.opp-lat1" workUrn="urn:cts:latinLit:tmp1353.tmp1353">
    <ti:label xml:lang="eng">Interpretatio Mystica Progenitorum Christi</ti:label>
    <ti:description xml:lang="eng">Alphanus Beneventianus Episcopus, Interpretatio Mystica Progenitorum Christi</ti:description>
  </ti:edition>
</ti:work>
