<ti:work xmlns:ti="http://chs.harvard.edu/xmlns/cts" groupUrn="urn:cts:latinLit:stoa0108f" xml:lang="lat" urn="urn:cts:latinLit:stoa0108f.stoa001">
  <ti:title xml:lang="eng">Ad Eugipium Presbyterum</ti:title>
  <ti:edition urn="urn:cts:latinLit:stoa0108f.stoa001.opp-lat1" workUrn="urn:cts:latinLit:stoa0108f.stoa001">
    <ti:label xml:lang="eng">Ad Eugipium Presbyterum</ti:label>
    <ti:description xml:lang="eng">Dionysius Exiguus, Ad Eugipium Presbyterum</ti:description>
  </ti:edition>
</ti:work>
