<ti:work xmlns:ti="http://chs.harvard.edu/xmlns/cts" groupUrn="urn:cts:latinLit:stoa0108d" xml:lang="lat" urn="urn:cts:latinLit:stoa0108d.stoa001">
  <ti:title xml:lang="eng">Epistola I 'Adversus Sabellianos' [Fragmentum]</ti:title>
  <ti:edition urn="urn:cts:latinLit:stoa0108d.stoa001.opp-lat1" workUrn="urn:cts:latinLit:stoa0108d.stoa001">
    <ti:label xml:lang="eng">Epistola I 'Adversus Sabellianos' [Fragmentum]</ti:label>
    <ti:description xml:lang="eng">SS Dionysius, Epistola I 'Adversus Sabellianos' [Fragmentum]</ti:description>
  </ti:edition>
</ti:work>
