<ti:work xmlns:ti="http://chs.harvard.edu/xmlns/cts" groupUrn="urn:cts:latinLit:tmp1410" xml:lang="lat" urn="urn:cts:latinLit:tmp1410.tmp1410">
  <ti:title xml:lang="eng">Appendix Ad Libros Regum</ti:title>
  <ti:edition urn="urn:cts:latinLit:tmp1410.tmp1410.opp-lat1" workUrn="urn:cts:latinLit:tmp1410.tmp1410">
    <ti:label xml:lang="eng">Appendix Ad Libros Regum</ti:label>
    <ti:description xml:lang="eng">Isidorus Hispalensis, Appendix Ad Libros Regum</ti:description>
  </ti:edition>
</ti:work>
