<ti:work xmlns:ti="http://chs.harvard.edu/xmlns/cts" groupUrn="urn:cts:latinLit:tmp953" xml:lang="lat" urn="urn:cts:latinLit:tmp953.tmp953">
  <ti:title xml:lang="eng">Sententia Ad Corinthios Primae</ti:title>
  <ti:edition urn="urn:cts:latinLit:tmp953.tmp953.opp-lat1" workUrn="urn:cts:latinLit:tmp953.tmp953">
    <ti:label xml:lang="eng">Sententia Ad Corinthios Primae</ti:label>
    <ti:description xml:lang="eng">Avitus Viennensis Episcopus, Sententia Ad Corinthios Primae</ti:description>
  </ti:edition>
</ti:work>
