<ti:work xmlns:ti="http://chs.harvard.edu/xmlns/cts" groupUrn="urn:cts:latinLit:stoa0100a" xml:lang="lat" urn="urn:cts:latinLit:stoa0100a.stoa001">
  <ti:title xml:lang="eng">Ad S. Cornelium appendices</ti:title>
  <ti:edition urn="urn:cts:latinLit:stoa0100a.stoa001.opp-lat1" workUrn="urn:cts:latinLit:stoa0100a.stoa001">
    <ti:label xml:lang="eng">Ad S. Cornelium appendices</ti:label>
    <ti:description xml:lang="eng">SS Cornelius, Ad S. Cornelium appendices</ti:description>
  </ti:edition>
</ti:work>
