<ti:work xmlns:ti="http://chs.harvard.edu/xmlns/cts" groupUrn="urn:cts:latinLit:tmp1442" xml:lang="lat" urn="urn:cts:latinLit:tmp1442.tmp1442">
  <ti:title xml:lang="eng">ORATIO PRO CURREPTIUNE VITÆ. FLENDA SEMPER PECCATA (Appendix XVIII)</ti:title>
  <ti:edition urn="urn:cts:latinLit:tmp1442.tmp1442.opp-lat1" workUrn="urn:cts:latinLit:tmp1442.tmp1442">
    <ti:label xml:lang="eng">ORATIO PRO CURREPTIUNE VITÆ. FLENDA SEMPER PECCATA (Appendix XVIII)</ti:label>
    <ti:description xml:lang="eng">, ORATIO PRO CURREPTIUNE VITÆ. FLENDA SEMPER PECCATA (Appendix XVIII)</ti:description>
  </ti:edition>
</ti:work>
